pypoly2tri/__init__.py
pypoly2tri/advancing_front.py
pypoly2tri/cdt.py
pypoly2tri/shapes.py
pypoly2tri/sweep.py
pypoly2tri/sweep_context.py
pypoly2tri/utils.py
pypoly2tri/licenses/poly2tri/LICENSE
pypoly2tri-0.0.3.dist-info/DESCRIPTION.rst
pypoly2tri-0.0.3.dist-info/METADATA
pypoly2tri-0.0.3.dist-info/RECORD
pypoly2tri-0.0.3.dist-info/WHEEL
pypoly2tri-0.0.3.dist-info/metadata.json
pypoly2tri-0.0.3.dist-info/top_level.txt
