Metadata-Version: 2.0
Name: pypoly2tri
Version: 0.0.3
Summary: pyPoly2Tri: a pure python implementation of poly2tri
Home-page: http://github.com/popupcad/pypoly2tri
Author: Dan Aukes
Author-email: danaukes@danaukes.com
License: MIT
Platform: UNKNOWN
Classifier: Programming Language :: Python
Classifier: Programming Language :: Python :: 3
